ordb/__init__.py
ordb/__main__.py
ordb/articles.db.gz
ordb/cli.py
ordb/config.py
ordb/core.py
ordb/display.py
ordb/pagination.py
ordb/utils.py
ordb/wizard.py
ordb-0.5.5.dist-info/licenses/LICENSE
ordb-0.5.5.dist-info/METADATA
ordb-0.5.5.dist-info/WHEEL
ordb-0.5.5.dist-info/entry_points.txt
ordb-0.5.5.dist-info/top_level.txt
ordb-0.5.5.dist-info/RECORD
