Metadata-Version: 2.4
Name: ordb
Version: 0.5.5
Summary: A fast, feature-rich command-line tool for searching the Norwegian bokmål dictionary with interactive search, cross-platform support, and comprehensive Norwegian language features
Home-page: https://github.com/kmlawson/ordb
Author: Konrad M. Lawson
Author-email: "Konrad M. Lawson" <kl@muninn.net>
License-Expression: MIT
Project-URL: Homepage, https://github.com/kmlawson/ordb
Project-URL: Repository, https://github.com/kmlawson/ordb.git
Project-URL: Issues, https://github.com/kmlawson/ordb/issues
Project-URL: Changelog, https://github.com/kmlawson/ordb/blob/main/CHANGELOG.md
Keywords: norwegian,dictionary,language,search,cli,norsk,bokmål
Classifier: Development Status :: 4 - Beta
Classifier: Environment :: Console
Classifier: Intended Audience :: Developers
Classifier: Intended Audience :: Education
Classifier: Intended Audience :: End Users/Desktop
Classifier: Natural Language :: Norwegian
Classifier: Operating System :: OS Independent
Classifier: Programming Language :: Python :: 3
Classifier: Programming Language :: Python :: 3.8
Classifier: Programming Language :: Python :: 3.9
Classifier: Programming Language :: Python :: 3.10
Classifier: Programming Language :: Python :: 3.11
Classifier: Programming Language :: Python :: 3.12
Classifier: Programming Language :: Python :: 3.13
Classifier: Topic :: Text Processing :: Linguistic
Classifier: Topic :: Utilities
Requires-Python: >=3.8
License-File: LICENSE
Provides-Extra: dev
Requires-Dist: pytest>=6.0; extra == "dev"
Requires-Dist: pytest-cov; extra == "dev"
Requires-Dist: black; extra == "dev"
Requires-Dist: flake8; extra == "dev"
Requires-Dist: mypy; extra == "dev"
Provides-Extra: test
Requires-Dist: pytest>=6.0; extra == "test"
Requires-Dist: pytest-cov; extra == "test"
Dynamic: license-file
